midas_open_parser/__init__.py
midas_open_parser/badc_csv.py
midas_open_parser/midas.py
midas_open_parser/test.py
midas_open_parser-0.1.27.dist-info/LICENSE.txt
midas_open_parser-0.1.27.dist-info/METADATA
midas_open_parser-0.1.27.dist-info/WHEEL
midas_open_parser-0.1.27.dist-info/top_level.txt
midas_open_parser-0.1.27.dist-info/RECORD
