Metadata-Version: 2.2
Name: midas_open_parser
Version: 0.1.27
Summary: A Python library for parsing BADC-CSV files from the MIDAS Open dataset
Author-email: TempoTerra <vanuan+midasparser@gmail.com>
Project-URL: Bug Tracker, https://github.com/tempoterra/midas_open_parser/issues
Project-URL: Documentation, https://tempoterra.github.io/midas_open_parser
Project-URL: Source Code, https://github.com/tempoterra/midas_open_parser
Keywords: atmospheric-science,midas-open,badc-csv,parser,environmental-data
Classifier: Programming Language :: Python :: 3
Classifier: License :: OSI Approved :: MIT License
Classifier: Operating System :: OS Independent
Classifier: Development Status :: 3 - Alpha
Classifier: Intended Audience :: Science/Research
Classifier: Topic :: Scientific/Engineering :: Atmospheric Science
Classifier: Topic :: Software Development :: Libraries :: Python Modules
Requires-Python: >=3.7
License-File: LICENSE.txt
